siamttview/__init__.py
siamttview/siamttview.py
SIAMTTVIEWS-5.1.1.dist-info/LICENSE
SIAMTTVIEWS-5.1.1.dist-info/METADATA
SIAMTTVIEWS-5.1.1.dist-info/WHEEL
SIAMTTVIEWS-5.1.1.dist-info/entry_points.txt
SIAMTTVIEWS-5.1.1.dist-info/top_level.txt
SIAMTTVIEWS-5.1.1.dist-info/RECORD
